{
  "data": {
    "listing": {
      "id": "01jgnsqn43p032f3cnd9c4eneb",
      "user_id": "01JGNSQN15DEJ7GZZEGKWPK6EW",
      "title": "sit quos rem",
      "description": "Deserunt blanditiis neque debitis recusandae dignissimos eius ut doloremque. Dolores cumque reiciendis blanditiis facere eligendi numquam deserunt. Illo voluptates distinctio est dolores cum. Magni voluptatibus ut ducimus doloribus maiores.",
      "price": 36723,
      "street_address": "4896 Estella Parks",
      "city": "Garthtown",
      "state": "Hawaii",
      "postal_code": "50980-4389",
      "country": "Bangladesh",
      "latitude": "-79.64079000",
      "longitude": "41.06836800",
      "images": [
        "https://avatars.githubusercontent.com/u/68756661?v=4",
        "https://avatars.githubusercontent.com/u/114558415?v=4"
      ],
      "bedrooms": 3,
      "bathrooms": 4,
      "features": ["Elevator", "Parking", "CCTV Camera"],
      "deleted_at": null,
      "created_at": "2025-01-03T10:00:20.000000Z",
      "updated_at": "2025-01-03T10:00:20.000000Z",
      "user": {
        "id": "01JGNSQN15DEJ7GZZEGKWPK6EW",
        "name": "Miss Vesta Blanda DVM",
        "email": "kreilly@example.com",
        "email_verified_at": "2025-01-03T10:00:20.000000Z",
        "created_at": "2025-01-03T10:00:20.000000Z",
        "updated_at": "2025-01-03T10:00:20.000000Z"
      }
    }
  },
  "message": "Listing show successful."
}
